backbone_translation-1.0.1-py3.12-nspkg.pth
basalam/backbone_translation/__init__.py
basalam/backbone_translation/translator.py
backbone_translation-1.0.1.dist-info/LICENSE
backbone_translation-1.0.1.dist-info/METADATA
backbone_translation-1.0.1.dist-info/WHEEL
backbone_translation-1.0.1.dist-info/namespace_packages.txt
backbone_translation-1.0.1.dist-info/top_level.txt
backbone_translation-1.0.1.dist-info/RECORD
