Metadata-Version: 2.1
Name: backbone-translation
Version: 1.0.1
Summary: Python Utilities & Basalam Micro-Services SDK
Home-page: https://github.com/basalam/backbone-translation
Author: Mojtabaa Habibain
Author-email: mojtabaa.hn@gmail.com
Classifier: Programming Language :: Python :: 3
Classifier: License :: OSI Approved :: MIT License
Classifier: Operating System :: OS Independent
Requires-Python: >=3.6
License-File: LICENSE
